{
    "[他][似乎]對[我]越來[越]不在意": [
        "或許他最近忙碌或煩惱，可能導致他對你的關心減少。",
        "你可以試著跟他溝通，問一問他是否有什麼在心事。",
        "請對方表達你的感受，告訴他你注意到他對你的態度有所改變。",
        "可以考慮和他約個時間，以認真的方式分享你的感受和期望。",
        "不要急著下結論，保持開放和理解的態度，也許他有合理的解釋。"
    ],
    "[對方][一點][都]不在乎[我]": [
        "或許對方的言行讓你有這樣的感受，但或許他們只是表達方式不同，仍然在乎你。",
        "有時候人們的關心方式可能與我們的期望不一致，但這並不代表他們不在乎你。",
        "或許你需要跟對方溝通，讓他們瞭解你的需求和感受，或許他們會理解並更加在乎你。",
        "有時候對方可能在忙於自己的事情，但這不表示他們不在乎你，也許他們只是暫時無法表現出來。",
        "有時候對方可能不擅於表達情感，但這不代表他們不在乎你。有些人用行動來表達愛和關心，或許你需要注意他們的行為才能感受到他們的關愛。"
    ],
    "[對方][根本]就不在乎[我]": [
        "或許他只是表現得不夠明顯，但不代表他不在乎你。",
        "人與人之間的表達方式不同，也許他只是以其他方式關心你。",
        "或許可以跟他溝通一下，讓他知道你對於他的關心有所期待。",
        "誰能真正瞭解他人的心思呢？也許他在意你的方式並不像你想的那樣。",
        "重要的是，你是否確定他對你真的不在乎呢？或許可以多觀察一下他的行動和言辭。"
    ],
    "[對方]不在乎[我]": [
        "或許對方表達關心和關注的方式不同，並不代表他們不在乎你。",
        "有時候人們可能因為忙碌或分心，而無法表達出對你的關心，不代表他們不在乎你。",
        "每個人都有自己的方式來表達關愛，也許你可以與對方溝通，瞭解彼此的需求。",
        "有些人可能不太善於表達情感，但他們的行動可能會表明他們在乎你。",
        "請記住，每個人都有他們自己的方式來表達關心，不要輕易下結論，可以與對方溝通，確認彼此的關係。"
    ],
    "[對方]不懂[我]": [
        "或許你可以試著更清楚地表達你的想法，讓對方更容易理解你。",
        "有時候，我們需要更耐心地解釋自己的觀點，讓對方明白我們的想法。",
        "瞭解彼此的觀點和背景往往能幫助我們更好地理解對方，建立更好的溝通。",
        "如果對方真的不懂你，建議你可以尋找其他方式來溝通，例如使用圖片、示意圖或其他視覺輔助工具。",
        "有時候，時間也是建立理解的關鍵，給彼此一些時間，或許對方會漸漸懂得你的想法。"
    ],
    "[我][常常]感到[自己]不被重視": [
        "我瞭解你的感受，常常感到自己不被重視確實讓人感到沮喪。",
        "感到自己不被重視是一種常見的情緒，很多人都有類似的經驗。",
        "有時候我們可能會感到不被重視，但這並不代表我們的價值就被否定了。",
        "值得記住的是，每個人都有不同的價值和貢獻，不要過度自我批評。",
        "如果你感到自己不被重視，可以試著與其他人溝通，讓他們瞭解你的想法和感受。"
    ],
    "[我][經常]被[他]忽視": [
        "我往往感到他對我漠不關心。",
        "他經常忽略我的存在，讓我感到被忽視。",
        "我常常被他忽視，而這讓我感到很無奈。",
        "他似乎總是對我視而不見，讓我感到被忽視。",
        "每次都被他忽視，這讓我覺得自己毫無價值。"
    ],
    "[我][經常]被[她]忘記": [
        "我常常被她忘記，這讓我感到有點受委屈。",
        "她總是忘記我，這讓我有點感到被冷落。",
        "我經常被她忘記，有時候我真的覺得自己不重要。",
        "每次被她忘記，我都覺得自己是一個容易被遺忘的人。",
        "我經常被她忘記，這讓我感到很無奈和失望。"
    ],
    "[我][經常]覺得[自己]被忘記": [
        "沒關係，每個人都有被忘記的時候，重要的是要記得堅持並展現自己的價值。",
        "不要灰心，有時候被忘記只是暫時的，下一次就會有更好的機會讓你被重視。",
        "讓自己的聲音被聽見需要時間，不要忘記繼續努力，相信自己的才能。",
        "可以嘗試主動出擊，主動參與事物，這樣可以讓更多人認識你的存在。",
        "雖然感到被忘記不是一件好事，但也許你可以利用這個機會尋找新的發展方向，展現不同的魅力。"
    ],
    "[我]不知道[他]是不[是][真心]愛[我]": [
        "無論如何，只有他自己才能回答你的問題，我無法確定他是否真心愛你。",
        "很難判斷他的內心真實感受，只有時間和相處才能揭示他對你的真正感情。",
        "或許你可以觀察他對你的細微舉動和關心，這可能會給你一些暗示。",
        "試著和他坦誠相見，傾聽他的話語和觀察他的行動，這有助於你更瞭解他對你的感覺。",
        "重要的是要相信自己的直覺和感受，並與他保持良好的溝通，這樣你就能更清楚地瞭解他是否真心愛你。"
    ],
    "[我]不確定[他]是不[是]還對[我]有[感情]": [
        "只有他自己知道他對你是否還有感情。",
        "可能需要更多的交流和互動才能確定他對你的感情狀態。",
        "或許可以直接向他詢問，以確定他是否對你還有感情。",
        "觀察他的言行舉止可能能提供一些線索，但最終只有他能給出確定的答案。",
        "有時候感情的變化是很難解釋的，但值得和他好好交流，以瞭解彼此的感受。"
    ]
}